autoreduce_utils/__init__.py
autoreduce_utils/migrate_credentials.py
autoreduce_utils/settings.py
autoreduce_utils/test_credentials.ini
autoreduce_utils/clients/__init__.py
autoreduce_utils/clients/abstract_client.py
autoreduce_utils/clients/connection_exception.py
autoreduce_utils/clients/icat_client.py
autoreduce_utils/clients/queue_client.py
autoreduce_utils/clients/settings/__init__.py
autoreduce_utils/clients/settings/client_settings.py
autoreduce_utils/clients/settings/client_settings_factory.py
autoreduce_utils/clients/settings/tests/__init__.py
autoreduce_utils/clients/settings/tests/test_client_settings.py
autoreduce_utils/clients/settings/tests/test_client_settings_factory.py
autoreduce_utils/clients/tests/__init__.py
autoreduce_utils/clients/tests/test_abstract_client.py
autoreduce_utils/clients/tests/test_icat_client.py
autoreduce_utils/clients/tests/test_queue_client.py
autoreduce_utils/clients/tools/__init__.py
autoreduce_utils/clients/tools/isisicat_prefix_mapping.py
autoreduce_utils/clients/tools/isisicat_prefix_mapping_logging_setup.py
autoreduce_utils/clients/tools/tests/__init__.py
autoreduce_utils/clients/tools/tests/test_isisicat_prefix_mapping.py
autoreduce_utils/message/__init__.py
autoreduce_utils/message/message.py
autoreduce_utils/message/tests/__init__.py
autoreduce_utils/message/tests/test_message.py
autoreduce_utils/message/validation/__init__.py
autoreduce_utils/message/validation/process.py
autoreduce_utils/message/validation/stages.py
autoreduce_utils/message/validation/validators.py
autoreduce_utils/message/validation/tests/__init__.py
autoreduce_utils/message/validation/tests/test_process.py
autoreduce_utils/message/validation/tests/test_stages.py
autoreduce_utils/message/validation/tests/test_validators.py
autoreduce_utils-0.1.3.dist-info/METADATA
autoreduce_utils-0.1.3.dist-info/WHEEL
autoreduce_utils-0.1.3.dist-info/entry_points.txt
autoreduce_utils-0.1.3.dist-info/top_level.txt
autoreduce_utils-0.1.3.dist-info/RECORD
